QGBx/__init__.py
QGBx/base/__init__.py
QGBx/base/analyzer.py
QGBx/base/device.py
QGBx/base/distribution.py
QGBx/base/generator.py
QGBx/base/visualiser.py
QGBx/devices/__init__.py
QGBx/devices/real_devices/__init__.py
QGBx/devices/real_devices/ibm_torino.py
QGBx/devices/simulators/__init__.py
QGBx/devices/simulators/noisless_simulators/pennylane_default.py
QGBx/devices/simulators/noisless_simulators/qiskit_aer.py
QGBx/devices/simulators/noisy_simulators/qiskit_fake_torino.py
QGBx/distributions/__init__.py
QGBx/distributions/exponential.py
QGBx/distributions/gaussian.py
QGBx/distributions/hadamard_QW.py
QGBx/distributions/layer_controlled.py
QGBx/distributions/peg_controlled.py
QGBx/distributions/optimized/exponential_optimized.py
QGBx/distributions/optimized/gaussian_optimized.py
QGBx/utils/__init__.py
QGBx/utils/tune_params.py
qgbx-0.1.1.dist-info/licenses/LICENSE
qgbx-0.1.1.dist-info/METADATA
qgbx-0.1.1.dist-info/WHEEL
qgbx-0.1.1.dist-info/top_level.txt
qgbx-0.1.1.dist-info/RECORD
