Metadata-Version: 2.4
Name: QGBx
Version: 0.1.1
Summary: An Open-Source Extensible Package for Simulating Various Statistical Distributions through a Multi-Dimensional Variational Quantum Galton Board!
Author-email: Ashraf Boussahi <a.boussahi@esi-sba.dz>, Abir Chekroun <a.chekroun@esi-sba.dz>
License: 
Project-URL: Homepage, https://github.com/AshrafBoussahi/QGBx
Requires-Python: >=3.8
License-File: LICENSE
Requires-Dist: matplotlib>=3.8.0
Requires-Dist: numpy>=2.3.2
Requires-Dist: PennyLane>=0.41.0
Requires-Dist: qiskit>=1.3.2
Requires-Dist: qiskit_ibm_runtime>=0.26.0
Requires-Dist: qiskit_ibm_transpiler>=0.13.1
Requires-Dist: scipy>=1.11.4
Requires-Dist: qiskit_ibm_ai_local_transpiler
Requires-Dist: qiskit[visualization]
Requires-Dist: qiskit_aer
Dynamic: license-file
